[{"line":1,"elements":[{"start_timestamp":"2025-06-07T07:58:05.543Z","line":5,"name":"Validate add place api with body","description":"","id":"validate-add-feature-apis;validate-add-place-api-with-body","type":"scenario","keyword":"Scenario","steps":[{"result":{"duration":16450000,"status":"passed"},"before":[{"result":{"duration":2988995200,"status":"passed"},"match":{"location":"com.BDD.StepDefinationFiles.Hook.getPlaceID()"}}],"line":6,"name":"Add place payload","match":{"location":"com.BDD.StepDefinationFiles.AddPlaceStepdefs.add_place_payload()"},"keyword":"Given "},{"result":{"duration":363811000,"status":"passed"},"before":[{"result":{"status":"passed"},"match":{"location":"com.BDD.StepDefinationFiles.Hook.getPlaceID()"}}],"line":7,"name":"user calls \"add\" with \"post\" https request","match":{"arguments":[{"val":"\"add\"","offset":11},{"val":"\"post\"","offset":22}],"location":"com.BDD.StepDefinationFiles.AddPlaceStepdefs.user_calls_with_https_request(java.lang.String,java.lang.String)"},"keyword":"When "},{"result":{"duration":3001700,"status":"passed"},"before":[{"result":{"status":"passed"},"match":{"location":"com.BDD.StepDefinationFiles.Hook.getPlaceID()"}}],"line":8,"name":"then api call get success with status code 200","match":{"arguments":[{"val":"200","offset":43}],"location":"com.BDD.StepDefinationFiles.AddPlaceStepdefs.then_api_call_get_success_with_status_code(java.lang.Integer)"},"keyword":"Then "},{"result":{"duration":20224300,"status":"passed"},"before":[{"result":{"status":"passed"},"match":{"location":"com.BDD.StepDefinationFiles.Hook.getPlaceID()"}}],"line":9,"name":"\"status\" in response boy is \"OK\"","match":{"arguments":[{"val":"\"status\"","offset":0},{"val":"\"OK\"","offset":28}],"location":"com.BDD.StepDefinationFiles.AddPlaceStepdefs.in_response_boy_is(java.lang.String,java.lang.String)"},"keyword":"And "}],"tags":[{"name":"@add_placeAPI"}]},{"start_timestamp":"2025-06-07T07:58:08.952Z","line":12,"name":"Validate get place api request","description":"","id":"validate-add-feature-apis;validate-get-place-api-request","type":"scenario","keyword":"Scenario","steps":[{"result":{"duration":1908770800,"status":"passed"},"before":[{"result":{"status":"passed"},"match":{"location":"com.BDD.StepDefinationFiles.Hook.getPlaceID()"}}],"line":13,"name":"user calls \"get\" with \"get\" https request","match":{"arguments":[{"val":"\"get\"","offset":11},{"val":"\"get\"","offset":22}],"location":"com.BDD.StepDefinationFiles.AddPlaceStepdefs.user_calls_with_https_request(java.lang.String,java.lang.String)"},"keyword":"Given "},{"result":{"status":"passed"},"before":[{"result":{"status":"passed"},"match":{"location":"com.BDD.StepDefinationFiles.Hook.getPlaceID()"}}],"line":14,"name":"then api call get success with status code 200","match":{"arguments":[{"val":"200","offset":43}],"location":"com.BDD.StepDefinationFiles.AddPlaceStepdefs.then_api_call_get_success_with_status_code(java.lang.Integer)"},"keyword":"Then "},{"result":{"duration":21916200,"status":"passed"},"before":[{"result":{"status":"passed"},"match":{"location":"com.BDD.StepDefinationFiles.Hook.getPlaceID()"}}],"line":15,"name":"\"name\" in response boy is \"Frontline House\"","match":{"arguments":[{"val":"\"name\"","offset":0},{"val":"\"Frontline House\"","offset":26}],"location":"com.BDD.StepDefinationFiles.AddPlaceStepdefs.in_response_boy_is(java.lang.String,java.lang.String)"},"keyword":"And "}],"tags":[{"name":"@get_placeAPI"}]},{"start_timestamp":"2025-06-07T07:58:10.884Z","line":29,"name":"Validate update place api with body","description":"","id":"validate-add-feature-apis;validate-update-place-api-with-body;;2","type":"scenario","keyword":"Scenario Outline","steps":[{"result":{"duration":2001500,"status":"passed"},"before":[{"result":{"status":"passed"},"match":{"location":"com.BDD.StepDefinationFiles.Hook.getPlaceID()"}}],"line":20,"name":"Update place payload with \"2703, town center lane, Sunnyvale 94086 CA, US\";","match":{"arguments":[{"val":"\"2703, town center lane, Sunnyvale 94086 CA, US\"","offset":26}],"location":"com.BDD.StepDefinationFiles.AddPlaceStepdefs.update_place_payload_with(java.lang.String)"},"keyword":"Given "},{"result":{"duration":2286308300,"status":"passed"},"before":[{"result":{"status":"passed"},"match":{"location":"com.BDD.StepDefinationFiles.Hook.getPlaceID()"}}],"line":21,"name":"user calls \"update\" with \"put\" https request","match":{"arguments":[{"val":"\"update\"","offset":11},{"val":"\"put\"","offset":25}],"location":"com.BDD.StepDefinationFiles.AddPlaceStepdefs.user_calls_with_https_request(java.lang.String,java.lang.String)"},"keyword":"When "},{"result":{"status":"passed"},"before":[{"result":{"status":"passed"},"match":{"location":"com.BDD.StepDefinationFiles.Hook.getPlaceID()"}}],"line":22,"name":"then api call get success with status code 200","match":{"arguments":[{"val":"200","offset":43}],"location":"com.BDD.StepDefinationFiles.AddPlaceStepdefs.then_api_call_get_success_with_status_code(java.lang.Integer)"},"keyword":"Then "},{"result":{"duration":21754000,"status":"passed"},"before":[{"result":{"status":"passed"},"match":{"location":"com.BDD.StepDefinationFiles.Hook.getPlaceID()"}}],"line":23,"name":"\"msg\" in response boy is \"Address successfully updated\"","match":{"arguments":[{"val":"\"msg\"","offset":0},{"val":"\"Address successfully updated\"","offset":25}],"location":"com.BDD.StepDefinationFiles.AddPlaceStepdefs.in_response_boy_is(java.lang.String,java.lang.String)"},"keyword":"And "},{"result":{"duration":2579359300,"status":"passed"},"before":[{"result":{"status":"passed"},"match":{"location":"com.BDD.StepDefinationFiles.Hook.getPlaceID()"}}],"line":24,"name":"user calls \"get\" with \"get\" https request","match":{"arguments":[{"val":"\"get\"","offset":11},{"val":"\"get\"","offset":22}],"location":"com.BDD.StepDefinationFiles.AddPlaceStepdefs.user_calls_with_https_request(java.lang.String,java.lang.String)"},"keyword":"Given "},{"result":{"duration":12667500,"status":"passed"},"before":[{"result":{"status":"passed"},"match":{"location":"com.BDD.StepDefinationFiles.Hook.getPlaceID()"}}],"line":25,"name":"\"address\" in response boy is \"2703, town center lane, Sunnyvale 94086 CA, US\"","match":{"arguments":[{"val":"\"address\"","offset":0},{"val":"\"2703, town center lane, Sunnyvale 94086 CA, US\"","offset":29}],"location":"com.BDD.StepDefinationFiles.AddPlaceStepdefs.in_response_boy_is(java.lang.String,java.lang.String)"},"keyword":"And "}],"tags":[{"name":"@update_placeAPI"}]},{"start_timestamp":"2025-06-07T07:58:15.790Z","line":33,"name":"Validate delete place api","description":"","id":"validate-add-feature-apis;validate-delete-place-api","type":"scenario","keyword":"Scenario","steps":[{"result":{"duration":2521200,"status":"passed"},"before":[{"result":{"status":"passed"},"match":{"location":"com.BDD.StepDefinationFiles.Hook.getPlaceID()"}}],"line":34,"name":"delete place payload","match":{"location":"com.BDD.StepDefinationFiles.AddPlaceStepdefs.delete_place_payload()"},"keyword":"Given "},{"result":{"duration":3262228100,"status":"passed"},"before":[{"result":{"status":"passed"},"match":{"location":"com.BDD.StepDefinationFiles.Hook.getPlaceID()"}}],"line":35,"name":"user calls \"delete\" with \"delete\" https request","match":{"arguments":[{"val":"\"delete\"","offset":11},{"val":"\"delete\"","offset":25}],"location":"com.BDD.StepDefinationFiles.AddPlaceStepdefs.user_calls_with_https_request(java.lang.String,java.lang.String)"},"keyword":"When "},{"result":{"duration":1004100,"status":"passed"},"before":[{"result":{"status":"passed"},"match":{"location":"com.BDD.StepDefinationFiles.Hook.getPlaceID()"}}],"line":36,"name":"then api call get success with status code 200","match":{"arguments":[{"val":"200","offset":43}],"location":"com.BDD.StepDefinationFiles.AddPlaceStepdefs.then_api_call_get_success_with_status_code(java.lang.Integer)"},"keyword":"Then "},{"result":{"duration":18991100,"status":"passed"},"before":[{"result":{"status":"passed"},"match":{"location":"com.BDD.StepDefinationFiles.Hook.getPlaceID()"}}],"line":37,"name":"\"status\" in response boy is \"OK\"","match":{"arguments":[{"val":"\"status\"","offset":0},{"val":"\"OK\"","offset":28}],"location":"com.BDD.StepDefinationFiles.AddPlaceStepdefs.in_response_boy_is(java.lang.String,java.lang.String)"},"keyword":"And "},{"result":{"duration":1821273400,"status":"passed"},"before":[{"result":{"status":"passed"},"match":{"location":"com.BDD.StepDefinationFiles.Hook.getPlaceID()"}}],"line":38,"name":"user calls \"get\" with \"get\" https request","match":{"arguments":[{"val":"\"get\"","offset":11},{"val":"\"get\"","offset":22}],"location":"com.BDD.StepDefinationFiles.AddPlaceStepdefs.user_calls_with_https_request(java.lang.String,java.lang.String)"},"keyword":"Given "},{"result":{"duration":22444900,"status":"passed"},"before":[{"result":{"status":"passed"},"match":{"location":"com.BDD.StepDefinationFiles.Hook.getPlaceID()"}}],"line":39,"name":"\"msg\" in response boy is \"Get operation failed, looks like place_id  doesn't exists\"","match":{"arguments":[{"val":"\"msg\"","offset":0},{"val":"\"Get operation failed, looks like place_id  doesn't exists\"","offset":25}],"location":"com.BDD.StepDefinationFiles.AddPlaceStepdefs.in_response_boy_is(java.lang.String,java.lang.String)"},"keyword":"And "}],"tags":[{"name":"@delete_placeAPI"}]}],"name":"Validate add feature APIs","description":"","id":"validate-add-feature-apis","keyword":"Feature","uri":"file:src/test/java/com/BDD/FeatureFiles/addPlace.feature","tags":[]}]